tweetai/__init__.py
tweetai/prompts.py
tweetai/tweetai.py
tweetai-0.1.1.dist-info/LICENSE
tweetai-0.1.1.dist-info/WHEEL
tweetai-0.1.1.dist-info/METADATA
tweetai-0.1.1.dist-info/RECORD
